pltRDF/__init__.py
pltRDF/calc_RDF.py
pltRDF/plot_matplotlib.py
pltRDF/plot_rdf.py
pltRDF/readGSD.py
pltRDF-0.1.6.dist-info/LICENSE
pltRDF-0.1.6.dist-info/METADATA
pltRDF-0.1.6.dist-info/WHEEL
pltRDF-0.1.6.dist-info/entry_points.txt
pltRDF-0.1.6.dist-info/top_level.txt
pltRDF-0.1.6.dist-info/RECORD
