Metadata-Version: 2.1
Name: pltRDF
Version: 0.1.6
Summary: A Python project to plot Radial distribution function (RDF) from GSD file
Home-page: https://github.com/sumitavakundu007/pltRDF
Author: Sumitava Kundu
Author-email: kundusumitava@gmail.com
License: UNKNOWN
Project-URL: Bug Reports, https://github.com/sumitavakundu007/pltRDF/issues
Project-URL: Say Thanks!, http://saythanks.io/to/example
Project-URL: Source, https://github.com/sumitavakundu007/pltRDF/
Keywords: sample,setuptools,development
Platform: UNKNOWN
Classifier: Intended Audience :: Developers
Classifier: Topic :: Software Development :: Build Tools
Classifier: License :: OSI Approved :: MIT License
Classifier: Programming Language :: Python :: 3
Classifier: Programming Language :: Python :: 3.6
Classifier: Programming Language :: Python :: 3.7
Classifier: Programming Language :: Python :: 3.8
Classifier: Programming Language :: Python :: 3.9
Requires-Python: >=3.6
License-File: LICENSE
Requires-Dist: gsd
Requires-Dist: scikit-build
Requires-Dist: freud-analysis
Requires-Dist: matplotlib
